football_tools/__init__.py
football_tools/cli.py
football_tools/statistics.py
football_tools/storage.py
football_tools/team_domain.py
football_tools/tests/__init__.py
football_tools/tests/test_storage.py
football_tools/tests/test_team_domain.py
football_tools-0.0.8.dist-info/LICENSE
football_tools-0.0.8.dist-info/METADATA
football_tools-0.0.8.dist-info/WHEEL
football_tools-0.0.8.dist-info/entry_points.txt
football_tools-0.0.8.dist-info/top_level.txt
football_tools-0.0.8.dist-info/RECORD
